{
  "users": [
    {
      "id": 207519769,
      "email": "daniel@mail.com",
      "password": "12345"
    },
    {
      "id": 366649407,
      "email": "francine@mail.com",
      "password": "12345"
    },
    {
      "id": 211303362,
      "email": "jana@mail.com",
      "password": "12345"
    },
    {
      "id": 966564470,
      "email": "tulla@mail.com",
      "password": "12345"
    },
    {
      "id": 364758889,
      "email": "jose@mail.com",
      "password": "12345"
    },
    {
      "id": 205104662,
      "email": "ana@mail.com",
      "password": "12345"
    },
    {
      "id": 326099263,
      "email": "luz@mail.com",
      "password": "123456"
    },
    {
      "id": 290509381,
      "email": "robson@mail.com",
      "password": "123456"
    }
  ],
  "users-data": [
    {
      "id": 207519769,
      "name": "Daniel",
      "birthDate": "10/05/1995",
      "occupation": "Jornalista",
      "country": "Brasil",
      "city": "São Paulo",
      "relationship": "Divorciado",
      "picture": "7.jpg"
    },
    {
      "id": 366649407,
      "name": "Francine",
      "birthDate": "15/06/1999",
      "occupation": "Advogada",
      "country": "Brasil",
      "city": "São Paulo",
      "relationship": "Namorando",
      "picture": "6.jpg"
    },
    {
      "id": 211303362,
      "name": "Jana",
      "birthDate": "09/08/1991",
      "occupation": "Cabeleireira",
      "country": "Brasil",
      "city": "Campinas",
      "relationship": "Namorando",
      "picture": "5.jpg"
    },
    {
      "id": 966564470,
      "name": "Tulla",
      "birthDate": "13/09/1970",
      "occupation": "Famosa",
      "country": "Brasil",
      "city": "Guarujá",
      "relationship": "Casado",
      "picture": "4.jpg"
    },
    {
      "id": 364758889,
      "name": "José Carlos",
      "birthDate": "06/12/1971",
      "occupation": "Câmera man",
      "country": "Brasil",
      "city": "Guarujá",
      "relationship": "Casado",
      "picture": "3.jpg"
    },
    {
      "id": 205104662,
      "name": "Ana",
      "birthDate": "10/10/1990",
      "occupation": "Programadora",
      "country": "Brasil",
      "city": "Campinas",
      "relationship": "Solteiro",
      "picture": "2.jpg"
    },
    {
      "id": 326099263,
      "name": "",
      "birthDate": "",
      "occupation": "",
      "country": "",
      "city": "",
      "relationship": "",
      "picture": "1.jpg"
    },
    {
      "id": 290509381,
      "name": "Robson",
      "birthDate": "10/04/2000",
      "occupation": "Mecânico",
      "country": "Brasil",
      "city": "Ribeirão Preto",
      "relationship": "Casado"
    }
  ]
}